pyflipt/__init__.py
pyflipt/client.py
pyflipt/models.py
pyflipt-0.1.0.dist-info/LICENSE
pyflipt-0.1.0.dist-info/WHEEL
pyflipt-0.1.0.dist-info/METADATA
pyflipt-0.1.0.dist-info/RECORD
