Metadata-Version: 2.1
Name: pyflipt
Version: 0.1.0
Summary: 
Author: Ferran Llamas
Author-email: llamas.arroniz@gmail.com
Requires-Python: >=3.8,<4.0
Classifier: Programming Language :: Python :: 3
Classifier: Programming Language :: Python :: 3.8
Classifier: Programming Language :: Python :: 3.9
Requires-Dist: aiohttp (>=3.7.4,<4.0.0)
Requires-Dist: pydantic (>=1.8.2,<2.0.0)
